EVRPTW_PR_ALNS/ALNS.py
EVRPTW_PR_ALNS/Initial.py
EVRPTW_PR_ALNS/__init__.py
EVRPTW_PR_ALNS/file_reader.py
EVRPTW_PR_ALNS/helper_function.py
EVRPTW_PR_ALNS/mip_check.py
EVRPTW_PR_ALNS/mip_model.py
EVRPTW_PR_ALNS/_algorithms/CI.py
EVRPTW_PR_ALNS/_algorithms/CR.py
EVRPTW_PR_ALNS/_algorithms/SI.py
EVRPTW_PR_ALNS/_algorithms/SR.py
EVRPTW_PR_ALNS/_algorithms/__init__.py
EVRPTW_PR_ALNS-0.0.3.dist-info/METADATA
EVRPTW_PR_ALNS-0.0.3.dist-info/WHEEL
EVRPTW_PR_ALNS-0.0.3.dist-info/top_level.txt
EVRPTW_PR_ALNS-0.0.3.dist-info/RECORD
